{"type":"node_created","timestamp":"2026-03-05T08:41:52.950346589Z","node":{"id":"1.11","type":"claim","statement":"(Recovery: Classical Barvinok-Pataki for M_n(C)) Setting A = M_n(C), the unique irreducible representation is the identity, so π_φ(A)' ≅ M_r(C) where r = rank(ρ_φ). Hence r² ≤ m + 1, or r² ≤ m when one constraint is trace normalisation. This recovers the Pataki (1998) bound.","inference":"assumption","workflow_state":"available","epistemic_state":"pending","taint_state":"unresolved","content_hash":"998060419c1d928c0cbb9543f46c31bf7ef98c2637656389195295c175e4411a","created":"2026-03-05T08:41:52.950327096Z","claimed_at":"0001-01-01T00:00:00Z"}}