{"type":"node_created","timestamp":"2026-02-28T16:10:31.247393328Z","node":{"id":"1.1.5","type":"claim","statement":"(Surjectivity of Φ via Radon-Nikodym). The map Φ is surjective onto F_{S(A)}(φ). Proof: Let ψ ∈ F_{S(A)}(φ). Then ψ ≤ λφ for some λ \u003e 0 (by characterisation of the face generated by φ). By the Radon-Nikodym theorem for states, there exists a unique T ∈ π_φ(A)' with 0 ≤ T ≤ λI such that ψ(a) = ⟨π_φ(a)Tξ_φ, ξ_φ⟩ for all a ∈ A. Since ψ is a state: ψ(1) = 1 = ⟨Tξ_φ, ξ_φ⟩. Hence T is in the domain of Φ and Φ(T) = ψ.","inference":"assumption","workflow_state":"available","epistemic_state":"pending","taint_state":"unresolved","content_hash":"2dbcb4c6f8cc5e81af126457a2fcacb2b02e081f1fa30e5da285bba2b5dc6340","created":"2026-02-28T16:10:31.247381088Z","claimed_at":"0001-01-01T00:00:00Z"}}