{"type":"node_created","timestamp":"2026-03-05T21:49:10.375836136Z","node":{"id":"1.18","type":"claim","statement":"(Recovery: Choi's theorem via BP) Let Φ: M_{d_A} → M_{d_B} be CPTP, represented by Choi matrix J ∈ PSD_{d_A·d_B} with Tr_B(J) = I_{d_A}. The TP condition constitutes m = d_A² real constraints. By BP (Theorem 1), the face dimension r² ≤ d_A² gives Kraus rank r ≤ d_A, recovering Choi's 1975 theorem.","inference":"assumption","workflow_state":"available","epistemic_state":"pending","taint_state":"unresolved","content_hash":"0405f205bd914a2cd05a634ad21c545ba9dbdae5d47fb37cba68ec3ba181d55d","created":"2026-03-05T21:49:10.375812262Z","claimed_at":"0001-01-01T00:00:00Z"}}