{"type":"challenge_raised","timestamp":"2026-02-28T16:33:56.299514172Z","challenge_id":"ch-ccc64daf6f9c7366","node_id":"1.3.1","target":"gap","reason":"The node claims 'A is a unital *-algebra and phi in S(A) is a state, so the GNS construction applies and the face-commutant correspondence (Node 1.1) holds.' This glosses over a critical issue: for a general unital *-algebra (not a C*-algebra), the GNS construction produces potentially UNBOUNDED representations. Specifically, pi_phi(a) for a in A may be an unbounded operator on H_phi (it is only defined on the dense domain pi_phi(A)xi_phi). The commutant pi_phi(A)' is standardly defined as {T in B(H) : T pi(a) = pi(a) T for all a}, which requires pi(a) to be bounded. For unbounded representations, the notion of commutant requires substantial modification (one must use the von Neumann algebra generated by the resolvent operators, or work with affiliated operators). The Alfsen-Shultz face-commutant correspondence (Thm 5.34 in their 2001 book) is stated and proved for C*-algebras, where GNS representations are automatically bounded. The node must either (a) restrict A to be a C*-algebra or a Banach *-algebra (where the GNS representation is bounded), or (b) explicitly address how the face-commutant correspondence extends to unbounded representations, with a reference.","severity":"critical","raised_by":""}