{"type":"challenge_raised","timestamp":"2026-02-28T16:43:30.068281853Z","challenge_id":"ch-2e94ce69c43a3392","node_id":"1.9.2","target":"completeness","reason":"Part (iv) A = M_2(C) ⊕ M_2(C): The claimed Spec = {0, 3, 7} is INCOMPLETE and the gap claim G ⊇ {1, 2} is FALSE.\n\nCOUNTEREXAMPLE for face dimension 1: Consider φ(a₁, a₂) = λ·⟨ψ₁|a₁|ψ₁⟩ + (1-λ)·⟨ψ₂|a₂|ψ₂⟩ with 0 \u003c λ \u003c 1, where ψ₁, ψ₂ are unit vectors (so φ₁, φ₂ are pure/rank-1 on each M_2(C) block). The GNS representation is π_φ = π₁ ⊕ π₂ on C² ⊕ C², with each πᵢ irreducible. The commutant is π_φ(A)' = C·I₁ ⊕ C·I₂ ≅ C ⊕ C. The self-adjoint part has dim_R = 2, so face dimension = 2 - 1 = 1.\n\nCOUNTEREXAMPLE for face dimension 4: Consider φ(a₁, a₂) = λ·⟨ψ|a₁|ψ⟩ + (1-λ)·(1/2)tr(a₂) with 0 \u003c λ \u003c 1, ψ a unit vector (rank-1 on first block), faithful on second block. Then π_φ(A)' ≅ C ⊕ M_2(C), dim_R(sa) = 1 + 4 = 5, face dim = 4.\n\nThe CORRECT spectrum is Spec(M_2(C) ⊕ M_2(C)) = {0, 1, 3, 4, 7}, and G = {2, 5, 6}. The claimed gap G ⊇ {1, 2} is false since 1 ∈ Spec. This is critical because example (iv) is meant to illustrate the gap phenomenon for direct sums, but the stated gap is wrong.\n\nFIX: Replace Spec = {0, 3, 7} with Spec = {0, 1, 3, 4, 7} and G ⊇ {1, 2} with G ⊇ {2} (or more precisely G = {2, 5, 6}).","severity":"critical","raised_by":""}