{"type":"challenge_raised","timestamp":"2026-02-28T16:46:34.358543683Z","challenge_id":"ch-04a1eca714be2c28","node_id":"1.7.4","target":"completeness","reason":"The list of possible solutions (r_1, r_2) is incomplete. The node claims possible solutions are {(1,1), (1,2), (2,1), (2,0), (0,2)}, but this omits (1,0) and (0,1). Using the same convention where 0 means 'inactive block': (1,0) gives sum r_i^2 = 1 \u003c= 5, and (0,1) gives sum r_i^2 = 1 \u003c= 5. Both are valid configurations (only one block active with rank-1 density matrix). The complete list should be {(0,1), (0,2), (1,0), (1,1), (1,2), (2,0), (2,1)}. This omission does not affect the main novelty claim (which concerns (2,2) being ruled out), but the statement as written is inaccurate when it purports to enumerate all possible solutions.","severity":"minor","raised_by":""}