{"type":"challenge_raised","timestamp":"2026-02-28T18:51:00.000000000Z","challenge_id":"ch-V1-185-facecorr","node_id":"1.8.5","target":"gap","reason":"CRITICAL GAP: The node claims 'Our framework applies to states on arbitrary C*-algebras, not just B(H)' but does NOT verify that the face-commutant correspondence (the key bridge between nodes 1.1 and 1.2) holds for arbitrary C*-algebras in the form needed.\n\nThe Alfsen-Shultz face-commutant correspondence (node 1.1) states: F_{S(A)}(phi) is affinely isomorphic to {T in pi_phi(A)'^+ : <T xi_phi, xi_phi> = 1}, and dim(F_{S(A)}(phi)) = dim_R(pi_phi(A)'^{sa}) - 1.\n\nFor this to hold for arbitrary C*-algebras, one needs: (a) the Radon-Nikodym theorem for states on general C*-algebras (Sakai's theorem: if psi <= lambda*phi for states on a C*-algebra A, then psi(a) = <pi_phi(a) T xi_phi, xi_phi> for unique T in pi_phi(A)' with 0 <= T <= lambda*I), and (b) that the map T -> omega_T is an affine isomorphism onto the face.\n\nWhile this is indeed a well-established result in operator algebra theory (Alfsen-Shultz 2001, Section 5; see also Bratteli-Robinson, Theorem 2.3.19), the extension from B(H) to general C*-algebras is NON-TRIVIAL and should be explicitly stated or referenced. The key subtlety is: for A = B(H), every state is a vector state in the universal representation, and the face-commutant correspondence is a fairly direct consequence of the spectral theorem. For a general C*-algebra A, the GNS representation pi_phi(A) may be a proper *-subalgebra of B(H_phi), and the commutant pi_phi(A)' is correspondingly larger. The correspondence still holds (by the Radon-Nikodym type theorem for C*-algebras), but this is the non-trivial content that makes node 1.8.5 a meaningful extension, and it deserves explicit justification rather than mere assertion.\n\nWithout this justification, the central claim of the node -- that the framework extends beyond B(H) -- is stated but not proved.","severity":"critical","raised_by":"verifier-V1"}